[{"aerodrome_name": "Melilla", "aerodrome_icao": "GEHM"}, {"aerodrome_name": "Kayes Dag-Dag", "aerodrome_icao": "GAKD", "aerodrome_iata": "KYS"}, {"aerodrome_name": "Sassandra", "aerodrome_icao": "DISS", "aerodrome_iata": "ZSS"}, {"aerodrome_name": "Gbangbatok", "aerodrome_icao": "GFGK", "aerodrome_iata": "GBK"}, {"aerodrome_name": "Korhogo", "aerodrome_icao": "DIKO", "aerodrome_iata": "HGO"}, {"aerodrome_name": "Inezgane", "aerodrome_icao": "GMAA"}, {"aerodrome_name": "Sasstown/Liberia", "aerodrome_icao": "GLST", "aerodrome_iata": "SAZ"}, {"aerodrome_name": "Seguela", "aerodrome_icao": "DISG", "aerodrome_iata": "SEO"}, {"aerodrome_name": "Matam/Ouro Sogui", "aerodrome_icao": "GOSM", "aerodrome_iata": "MAX"}, {"aerodrome_name": "Ziguinchor", "aerodrome_icao": "GOGG", "aerodrome_iata": "ZIG"}, {"aerodrome_name": "Boundiali", "aerodrome_icao": "DIBI", "aerodrome_iata": "BXI"}, {"aerodrome_name": "Sikasso/Dignangan", "aerodrome_icao": "GASO", "aerodrome_iata": "KSS"}, {"aerodrome_name": "Tambacounda", "aerodrome_icao": "GOTT", "aerodrome_iata": "TUD"}, {"aerodrome_name": "Nara/Keibane", "aerodrome_icao": "GANK", "aerodrome_iata": "NRM"}, {"aerodrome_name": "Abengourou", "aerodrome_icao": "DIAU", "aerodrome_iata": "OGO"}, {"aerodrome_name": "El Berriel", "aerodrome_icao": "GCLB"}, {"aerodrome_name": "Bubaque", "aerodrome_icao": "GGBU", "aerodrome_iata": "BQE"}, {"aerodrome_name": "Taroudant", "aerodrome_icao": "GMMO"}, {"aerodrome_name": "Zagora", "aerodrome_icao": "GMAZ", "aerodrome_iata": "OZG"}, {"aerodrome_name": "Casablanca/Mohammed V", "aerodrome_icao": "GMMN", "aerodrome_iata": "CMN"}, {"aerodrome_name": "Bondoukou/Soko", "aerodrome_icao": "DIBU", "aerodrome_iata": "BDK"}, {"aerodrome_name": "Boke(Baralande)/Guin", "aerodrome_icao": "GUOK", "aerodrome_iata": "BKJ"}, {"aerodrome_name": "Nouakchott-Oumtounsy", "aerodrome_icao": "GQNO", "aerodrome_iata": "NKC"}, {"aerodrome_name": "Laayoune/Hassan I", "aerodrome_icao": "GMML", "aerodrome_iata": "EUN"}, {"aerodrome_name": "Kedougou", "aerodrome_icao": "GOTK", "aerodrome_iata": "KGG"}, {"aerodrome_icao": "GMMG"}, {"aerodrome_name": "N'Zerekore(Konia)", "aerodrome_icao": "GUNZ", "aerodrome_iata": "NZE"}, {"aerodrome_name": "Kaedi", "aerodrome_icao": "GQNK", "aerodrome_iata": "KED"}, {"aerodrome_name": "Yengema", "aerodrome_icao": "GFYE", "aerodrome_iata": "WYE"}, {"aerodrome_name": "Dakhla", "aerodrome_icao": "GMMH", "aerodrome_iata": "VIL"}, {"aerodrome_name": "Sinoe/Greenville", "aerodrome_icao": "GLGE", "aerodrome_iata": "SNI"}, {"aerodrome_name": "Nema", "aerodrome_icao": "GQNI", "aerodrome_iata": "EMN"}, {"aerodrome_name": "Agostinho Neto/Santo Antao Island", "aerodrome_icao": "GVAN", "aerodrome_iata": "NTO"}, {"aerodrome_name": "Aioun El Atrouss", "aerodrome_icao": "GQNA", "aerodrome_iata": "AEO"}, {"aerodrome_name": "Monrovia Intl/Liberi", "aerodrome_icao": "GLRB", "aerodrome_iata": "ROB"}, {"aerodrome_name": "Odienne", "aerodrome_icao": "DIOD", "aerodrome_iata": "KEO"}, {"aerodrome_name": "Oujda Angads", "aerodrome_icao": "GMFO", "aerodrome_iata": "OUD"}, {"aerodrome_name": "Ouarzazate", "aerodrome_icao": "GMMZ", "aerodrome_iata": "OZZ"}, {"aerodrome_name": "Tenerife Norte", "aerodrome_icao": "GCXO", "aerodrome_iata": "TFN"}, {"aerodrome_name": "Kolda/Sare Bidji", "aerodrome_icao": "GOGK", "aerodrome_iata": "KDA"}, {"aerodrome_name": "Bakel", "aerodrome_icao": "GOTB", "aerodrome_iata": "BXE"}, {"aerodrome_name": "Zoueratt/Tazadit", "aerodrome_icao": "GQPZ", "aerodrome_iata": "OUZ"}, {"aerodrome_name": "Sao Filipe/ Fogo Island", "aerodrome_icao": "GVSF", "aerodrome_iata": "SFL"}, {"aerodrome_name": "Nouadhibou", "aerodrome_icao": "GQPP", "aerodrome_iata": "NDB"}, {"aerodrome_name": "Cap Skirring", "aerodrome_icao": "GOGS", "aerodrome_iata": "CSK"}, {"aerodrome_name": "Freetown", "aerodrome_icao": "GFLL", "aerodrome_iata": "FNA"}, {"aerodrome_icao": "GMSL"}, {"aerodrome_name": "Mosteiros/Fogo Island", "aerodrome_icao": "GVMT", "aerodrome_iata": "MTI"}, {"aerodrome_name": "Monrovia/Spriggs Pay", "aerodrome_icao": "GLMR", "aerodrome_iata": "MLW"}, {"aerodrome_icao": "GMMA"}, {"aerodrome_name": "Faranah/Badala", "aerodrome_icao": "GUFH", "aerodrome_iata": "FAA"}, {"aerodrome_name": "Yelimane", "aerodrome_icao": "GAYE", "aerodrome_iata": "EYL"}, {"aerodrome_name": "Sao Pedro/Cesaria Evora International ", "aerodrome_icao": "GVSV", "aerodrome_iata": "VXE"}, {"aerodrome_name": "Kiffa", "aerodrome_icao": "GQNF", "aerodrome_iata": "KFA"}, {"aerodrome_name": "Conakry/Gbessia", "aerodrome_icao": "GUCY", "aerodrome_iata": "CKY"}, {"aerodrome_name": "Atar", "aerodrome_icao": "GQPA", "aerodrome_iata": "ATR"}, {"aerodrome_name": "Fuerteventura", "aerodrome_icao": "GCFV", "aerodrome_iata": "FUE"}, {"aerodrome_name": "Daloa", "aerodrome_icao": "DIDL", "aerodrome_iata": "DJO"}, {"aerodrome_name": "Lanzarote", "aerodrome_icao": "GCRR", "aerodrome_iata": "ACE"}, {"aerodrome_name": "San Pedro", "aerodrome_icao": "DISP", "aerodrome_iata": "SPY"}, {"aerodrome_name": "Voinjama/Liberia", "aerodrome_icao": "GLVA", "aerodrome_iata": "VOI"}, {"aerodrome_name": "Errachidia/Moulay Ali Cherif", "aerodrome_icao": "GMFK", "aerodrome_iata": "ERH"}, {"aerodrome_name": "Hierro", "aerodrome_icao": "GCHI", "aerodrome_iata": "VDE"}, {"aerodrome_name": "Praia/Nelson Mandela International", "aerodrome_icao": "GVNP", "aerodrome_iata": "RAI"}, {"aerodrome_name": "Dakar/Leopold Sedar Senghor", "aerodrome_icao": "GOOY", "aerodrome_iata": "DKR"}, {"aerodrome_name": "Guelmime", "aerodrome_icao": "GMAG", "aerodrome_iata": "GLN"}, {"aerodrome_name": "Kenitra ", "aerodrome_icao": "GMMP"}, {"aerodrome_name": "Kenema/Sierra Leone", "aerodrome_icao": "GFKE", "aerodrome_iata": "KEN"}, {"aerodrome_name": "Rabil/Aristides Pereira International ", "aerodrome_icao": "GVBA", "aerodrome_iata": "BVC"}, {"aerodrome_name": "La Palma", "aerodrome_icao": "GCLA", "aerodrome_iata": "SPC"}, {"aerodrome_name": "Labe(Tata)/Guinea", "aerodrome_icao": "GULB", "aerodrome_iata": "LEK"}, {"aerodrome_name": "Bouarfa", "aerodrome_icao": "GMFB", "aerodrome_iata": "UAR"}, {"aerodrome_name": "Bouna/Tehini", "aerodrome_icao": "DIBN", "aerodrome_iata": "BQO"}, {"aerodrome_name": "Simenti", "aerodrome_icao": "GOTS", "aerodrome_iata": "SMY"}, {"aerodrome_name": "Gran Canaria", "aerodrome_icao": "GCLP", "aerodrome_iata": "LPA"}, {"aerodrome_name": "Adeje", "aerodrome_icao": "GCAD"}, {"aerodrome_name": "Tidjikja", "aerodrome_icao": "GQND", "aerodrome_iata": "TIY"}, {"aerodrome_name": "Richard-Toll", "aerodrome_icao": "GOSR", "aerodrome_iata": "RDT"}, {"aerodrome_name": "Tchien/Liberia", "aerodrome_icao": "GLTN", "aerodrome_iata": "THC"}, {"aerodrome_name": "Essaouira Mogador Intl", "aerodrome_icao": "GMMI", "aerodrome_iata": "ESU"}, {"aerodrome_name": "Tenerife Norte", "aerodrome_icao": "GCXM"}, {"aerodrome_name": "Bir Moghrein", "aerodrome_icao": "GQPT"}, {"aerodrome_name": "Maio/Maio Island", "aerodrome_icao": "GVMA", "aerodrome_iata": "MMO"}, {"aerodrome_name": "Sal/Amilcar Cabral International Airport", "aerodrome_icao": "GVAC", "aerodrome_iata": "SID"}, {"aerodrome_name": "Tabou", "aerodrome_icao": "DITB", "aerodrome_iata": "TXU"}, {"aerodrome_name": "La Gomera", "aerodrome_icao": "GCGM", "aerodrome_iata": "GMZ"}, {"aerodrome_name": "Touba/Mahana", "aerodrome_icao": "DITM", "aerodrome_iata": "TOZ"}, {"aerodrome_name": "Tetouan/Saniat Rmel", "aerodrome_icao": "GMTN", "aerodrome_iata": "TTU"}, {"aerodrome_name": "Nioro", "aerodrome_icao": "GANR", "aerodrome_iata": "NIX"}, {"aerodrome_name": "Al Hoceima/Cherif El Idrissi", "aerodrome_icao": "GMTA", "aerodrome_iata": "AHU"}, {"aerodrome_name": "Kabala/Sierra Leone", "aerodrome_icao": "GFKB", "aerodrome_iata": "KBA"}, {"aerodrome_name": "Benslimane National", "aerodrome_icao": "GMMB", "aerodrome_iata": "GMD"}, {"aerodrome_name": "Tanger Ibn Batouta", "aerodrome_icao": "GMTT", "aerodrome_iata": "TNG"}, {"aerodrome_name": "Rabat/Sale", "aerodrome_icao": "GMME", "aerodrome_iata": "RBA"}, {"aerodrome_name": "Bissau / Osvaldo Viera", "aerodrome_icao": "GGOV", "aerodrome_iata": "OXB"}, {"aerodrome_name": "Kenieba", "aerodrome_icao": "GAKA", "aerodrome_iata": "KNZ"}, {"aerodrome_name": "Man", "aerodrome_icao": "DIMN", "aerodrome_iata": "MJC"}, {"aerodrome_name": "Tan-Tan/Plage Blanche", "aerodrome_icao": "GMAT", "aerodrome_iata": "TTA"}, {"aerodrome_icao": "GMFM"}, {"aerodrome_name": "Podor", "aerodrome_icao": "GOSP", "aerodrome_iata": "POD"}, {"aerodrome_name": "Fes Saiss", "aerodrome_icao": "GMFF", "aerodrome_iata": "FEZ"}, {"aerodrome_name": "Goundam", "aerodrome_icao": "GAGM", "aerodrome_iata": "GUD"}, {"aerodrome_name": "Selibaby", "aerodrome_icao": "GQNS", "aerodrome_iata": "SEY"}, {"aerodrome_name": "Felix Houphouet Boigny D'Abidjan", "aerodrome_icao": "DIAP", "aerodrome_iata": "ABJ"}, {"aerodrome_name": "Saint-Louis", "aerodrome_icao": "GOSS", "aerodrome_iata": "XLS"}, {"aerodrome_name": "Aerodrome De Yamoussoukro", "aerodrome_icao": "DIYO", "aerodrome_iata": "ASK"}, {"aerodrome_name": "Bonthe", "aerodrome_icao": "GFBN", "aerodrome_iata": "BTE"}, {"aerodrome_name": "Ifrane", "aerodrome_icao": "GMFI"}, {"aerodrome_name": "Guiglo", "aerodrome_icao": "DIGL", "aerodrome_iata": "GGO"}, {"aerodrome_name": "Marrakech/Menara", "aerodrome_icao": "GMMX", "aerodrome_iata": "RAK"}, {"aerodrome_name": "Timbedra", "aerodrome_icao": "GQNH", "aerodrome_iata": "TMD"}, {"aerodrome_name": "Mopti/Ambodedjo", "aerodrome_icao": "GAMB", "aerodrome_iata": "MZI"}, {"aerodrome_name": "Banjul Intl", "aerodrome_icao": "GBYD", "aerodrome_iata": "BJL"}, {"aerodrome_name": "Bamako/Senou", "aerodrome_icao": "GABS", "aerodrome_iata": "BKO"}, {"aerodrome_name": "Preguica/Sao Nicolau Island", "aerodrome_icao": "GVSN", "aerodrome_iata": "SNE"}, {"aerodrome_name": "Cape Palmas/Harper", "aerodrome_icao": "GLCP", "aerodrome_iata": "CPA"}, {"aerodrome_name": "Melilla", "aerodrome_icao": "GEML", "aerodrome_iata": "MLN"}, {"aerodrome_name": "Bouake", "aerodrome_icao": "DIBK", "aerodrome_iata": "BYK"}, {"aerodrome_name": "Tenerife Sur/Reina Sofia", "aerodrome_icao": "GCTS", "aerodrome_iata": "TFS"}, {"aerodrome_name": "Agadir/Al Massira", "aerodrome_icao": "GMAD", "aerodrome_iata": "AGA"}, {"aerodrome_name": "Beni Mellal International", "aerodrome_icao": "GMMD"}, {"aerodrome_name": "Nador/El Aroui", "aerodrome_icao": "GMMW", "aerodrome_iata": "NDR"}, {"aerodrome_name": "Casablanca Tit Mellil", "aerodrome_icao": "GMMT", "aerodrome_iata": "CAS"}]